hangman/__init__.py
hangman/dictionary.txt
hangman/main.py
hangman/states.py
gallow_game-0.0.1.dist-info/METADATA
gallow_game-0.0.1.dist-info/WHEEL
gallow_game-0.0.1.dist-info/RECORD
