Metadata-Version: 2.1
Name: gallow_game
Version: 0.0.1
Summary: 
Author: Nick Mozganov
Author-email: nick-mozg1@mail.ru
Requires-Python: >=3.10.7,<4.0.0
Classifier: Programming Language :: Python :: 3
Classifier: Programming Language :: Python :: 3.11
